factiva/news/__init__.py
factiva/news/__version__.py
factiva/news/bulknews.py
factiva/news/snapshot/__init__.py
factiva/news/snapshot/jobs.py
factiva/news/snapshot/query.py
factiva/news/snapshot/snapshot.py
factiva/news/stream/__init__.py
factiva/news/stream/listener.py
factiva/news/stream/stream.py
factiva/news/stream/subscription.py
factiva/news/taxonomy/__init__.py
factiva/news/taxonomy/company.py
factiva/news/taxonomy/taxonomy.py
factiva/news/tools/__init__.py
factiva/news/tools/bq_schemas.py
factiva/news/tools/listener_handlers.py
factiva_news-0.2.5.dist-info/LICENSE
factiva_news-0.2.5.dist-info/METADATA
factiva_news-0.2.5.dist-info/WHEEL
factiva_news-0.2.5.dist-info/top_level.txt
factiva_news-0.2.5.dist-info/RECORD
