Metadata-Version: 2.1
Name: factiva-news
Version: 0.2.5
Summary: Python package to interact with Factiva news-related APIs. Services are described in the Dow Jones Developer Platform.
Home-page: https://developer.dowjones.com/
Author: Dow Jones Customer Engineers
Author-email: customer.solutions@dowjones.com
License: MIT
Project-URL: GitHub, https://github.com/dowjones/factiva-news-python
Project-URL: Documentation, https://factiva-news-python.readthedocs.io/
Project-URL: Bug Tracker, https://github.com/dowjones/factiva-news-python/issues
Keywords: news,news aggregator,risk,compliance,nlp,alternative data,factiva,trading news,market movers
Classifier: Development Status :: 4 - Beta
Classifier: Intended Audience :: Science/Research
Classifier: Intended Audience :: Financial and Insurance Industry
Classifier: Operating System :: OS Independent
Classifier: Topic :: Office/Business :: News/Diary
Classifier: Topic :: Office/Business :: Financial :: Investment
Classifier: Topic :: Scientific/Engineering :: Artificial Intelligence
Classifier: License :: OSI Approved :: MIT License
Classifier: Programming Language :: Python :: 3.7
Classifier: Programming Language :: Python :: 3.8
Classifier: Programming Language :: Python :: 3.9
Classifier: Programming Language :: Python :: 3.10
Requires-Python: >=3.7
License-File: LICENSE
Requires-Dist: factiva-core (>=0.2.3)
Requires-Dist: fastavro
Requires-Dist: google-cloud-core
Requires-Dist: google-cloud-pubsub
Requires-Dist: google-cloud-bigquery
Requires-Dist: pymongo
